lab04/top.sv
`default_nettype none

module top (
  // I/O ports
  input  logic hz100, reset,
  input  logic [20:0] pb,
  output logic [7:0] left, right,
         ss7, ss6, ss5, ss4, ss3, ss2, ss1, ss0,
  output logic red, green, blue,

  // UART ports
  output logic [7:0] txdata,
  input  logic [7:0] rxdata,
  output logic txclk, rxclk,
  input  logic txready, rxready
);

  // Your code goes here...
  
  //Step 1
  
  //assign ss0[6:0] = pb[6:0];  
  
  //Step 2
  
  bargraph num_1(.out({left[7:0],right[7:0]}), .in(pb[15:0]));
  
  //Step 3
  
  decode3to8 ins_and_outs(.out({ss7[7], ss6[7], ss5[7], ss4[7], ss3[7], ss2[7], ss1[7], ss0[7]}), .in(pb[2:0]));

endmodule

// Add your submodules below.

module bargraph ( 
    input logic [15:0]in,
    output logic [15:0]out
);
    assign out[0] = |in[15:0];
    assign out[1] = |in[15:1];
    assign out[2] = |in[15:2];
    assign out[3] = |in[15:3];
    assign out[4] = |in[15:4];
    assign out[5] = |in[15:5];
    assign out[6] = |in[15:6];
    assign out[7] = |in[15:7];
    assign out[8] = |in[15:8];
    assign out[9] = |in[15:9];
    assign out[10] = |in[15:10];
    assign out[11] = |in[15:11];
    assign out[12] = |in[15:12];
    assign out[13] = |in[15:13];
    assign out[14] = |in[15:14];
    assign out[15] = |in[15:15];
    
endmodule

module decode3to8 (
    output logic [7:0]out,
    input logic [2:0]in
);
                
assign out[0] = in[2:0] == 3'b000;
assign out[1] = in[2:0] == 3'b001;
assign out[2] = in[2:0] == 3'b010;
assign out[3] = in[2:0] == 3'b011;
assign out[4] = in[2:0] == 3'b100;
assign out[5] = in[2:0] == 3'b101;
assign out[6] = in[2:0] == 3'b110;
assign out[7] = in[2:0] == 3'b111;

endmodule

lab04/tb.sv
module lab_testbench ();

logic hz100;
logic reset;
logic [20:0] pb;
logic [7:0] ss7,ss6,ss5,ss4,ss3,ss2,ss1,ss0;
logic [7:0] left,right;
logic red,green,blue;
logic [7:0] rxdata, txdata;
logic txclk, rxclk, rxready, txready;

top top_inst(
      hz100, reset, pb,
      left, right, ss7, ss6, ss5, ss4, ss3, ss2, ss1, ss0,
      red, green, blue,
      txdata,
      rxdata,
      txclk, rxclk,
      txready, rxready
);

integer STDERR = 32'h8000_0002;

logic errored;

integer i;
logic [15:0] corr;
logic [7:0] ans;
logic [1023:0] testname;
initial begin
    $dumpfile ("lab04.vcd");
    $dumpvars (0, lab_testbench);
    errored = 0;
    // put tests here
    testname = "Bargraph Tests";
    pb = 0;
    #10;
    pb = 1; corr = 16'b1;
    #10;
    for (pb = 1; ~pb[16]; pb <<= 1) begin
        #10;
        if ({left, right} != corr) begin
            $fdisplay(STDERR,"ERROR: Expected {left,right} = 0x%x but got 0x%x when pb = 0x%x", corr, {left, right}, pb);
            errored = 1;
        end
        corr = (corr << 1) | 16'b1;
    end

    testname = "Decoder Tests";
    pb = 0;
    corr = 8'b1;
    for (pb = 0; pb[3:0] != 4'd8; pb += 1) begin
        #10;
        ans = {ss7[7], ss6[7], ss5[7], ss4[7], ss3[7], ss2[7], ss1[7], ss0[7]};
        if (ans != corr) begin
            $fdisplay(STDERR,"ERROR: Expected {...ssX[7]...} = 0x%x but got 0x%x when pb = 0b%b", corr, ans, pb[3:0]);
            errored = 1;
        end
        corr <<= 1;
    end
    if (errored == 0)
        $finish;
    else
        $stop;
end

endmodule

lab04/lab04.vcd
$date
	Wed Sep 22 12:13:13 2021
$end
$version
	Icarus Verilog
$end
$timescale
	1s
$end
$scope module lab_testbench $end
$var wire 8 ! txdata [7:0] $end
$var wire 1 " txclk $end
$var wire 8 # ss7 [7:0] $end
$var wire 8 $ ss6 [7:0] $end
$var wire 8 % ss5 [7:0] $end
$var wire 8 & ss4 [7:0] $end
$var wire 8 ' ss3 [7:0] $end
$var wire 8 ( ss2 [7:0] $end
$var wire 8 ) ss1 [7:0] $end
$var wire 8 * ss0 [7:0] $end
$var wire 1 + rxclk $end
$var wire 8 , right [7:0] $end
$var wire 1 - red $end
$var wire 8 . left [7:0] $end
$var wire 1 / green $end
$var wire 1 0 blue $end
$var reg 8 1 ans [7:0] $end
$var reg 16 2 corr [15:0] $end
$var reg 1 3 errored $end
$var reg 1 4 hz100 $end
$var reg 21 5 pb [20:0] $end
$var reg 1 6 reset $end
$var reg 8 7 rxdata [7:0] $end
$var reg 1 8 rxready $end
$var reg 1024 9 testname [1023:0] $end
$var reg 1 : txready $end
$var integer 32 ; STDERR [31:0] $end
$scope module top_inst $end
$var wire 1 4 hz100 $end
$var wire 21 < pb [20:0] $end
$var wire 1 6 reset $end
$var wire 8 = rxdata [7:0] $end
$var wire 1 8 rxready $end
$var wire 1 : txready $end
$var wire 8 > ss7 [7:0] $end
$var wire 8 ? ss6 [7:0] $end
$var wire 8 @ ss5 [7:0] $end
$var wire 8 A ss4 [7:0] $end
$var wire 8 B ss3 [7:0] $end
$var wire 8 C ss2 [7:0] $end
$var wire 8 D ss1 [7:0] $end
$var wire 8 E ss0 [7:0] $end
$var wire 8 F right [7:0] $end
$var wire 8 G left [7:0] $end
$var reg 1 0 blue $end
$var reg 1 / green $end
$var reg 1 - red $end
$var reg 1 + rxclk $end
$var reg 1 " txclk $end
$var reg 8 H txdata [7:0] $end
$scope module ins_and_outs $end
$var wire 3 I in [2:0] $end
$var wire 8 J out [7:0] $end
$upscope $end
$scope module num_1 $end
$var wire 16 K in [15:0] $end
$var wire 16 L out [15:0] $end
$upscope $end
$upscope $end
$upscope $end
$enddefinitions $end
#0
$dumpvars
b0 L
b0 K
b1 J
b0 I
bx H
b0 G
b0 F
b1zzzzzzz E
b0zzzzzzz D
b0zzzzzzz C
b0zzzzzzz B
b0zzzzzzz A
b0zzzzzzz @
b0zzzzzzz ?
b0zzzzzzz >
bx =
b0 <
b10000000000000000000000000000010 ;
x:
b100001001100001011100100110011101110010011000010111000001101000001000000101010001100101011100110111010001110011 9
x8
bx 7
x6
b0 5
x4
03
bx 2
bx 1
x0
x/
b0 .
x-
b0 ,
x+
b1zzzzzzz *
b0zzzzzzz )
b0zzzzzzz (
b0zzzzzzz '
b0zzzzzzz &
b0zzzzzzz %
b0zzzzzzz $
b0zzzzzzz #
x"
bx !
$end
#10
b1 ,
b1 F
b0zzzzzzz *
b0zzzzzzz E
b1zzzzzzz )
b1zzzzzzz D
b1 L
b1 K
b10 J
b1 I
b1 2
b1 5
b1 <
#30
b11 ,
b11 F
b11 L
b0zzzzzzz )
b0zzzzzzz D
b1zzzzzzz (
b1zzzzzzz C
b10 K
b100 J
b10 I
b10 5
b10 <
b11 2
#40
b111 ,
b111 F
b111 L
b0zzzzzzz (
b0zzzzzzz C
b1zzzzzzz &
b1zzzzzzz A
b100 K
b10000 J
b100 I
b100 5
b100 <
b111 2
#50
b1111 ,
b1111 F
b1111 L
b1zzzzzzz *
b1zzzzzzz E
b0zzzzzzz &
b0zzzzzzz A
b1000 K
b1 J
b0 I
b1000 5
b1000 <
b1111 2
#60
b11111 ,
b11111 F
b11111 L
b10000 K
b10000 5
b10000 <
b11111 2
#70
b111111 ,
b111111 F
b111111 L
b100000 K
b100000 5
b100000 <
b111111 2
#80
b1111111 ,
b1111111 F
b1111111 L
b1000000 K
b1000000 5
b1000000 <
b1111111 2
#90
b11111111 ,
b11111111 F
b11111111 L
b10000000 K
b10000000 5
b10000000 <
b11111111 2
#100
b1 .
b1 G
b111111111 L
b100000000 K
b100000000 5
b100000000 <
b111111111 2
#110
b11 .
b11 G
b1111111111 L
b1000000000 K
b1000000000 5
b1000000000 <
b1111111111 2
#120
b111 .
b111 G
b11111111111 L
b10000000000 K
b10000000000 5
b10000000000 <
b11111111111 2
#130
b1111 .
b1111 G
b111111111111 L
b100000000000 K
b100000000000 5
b100000000000 <
b111111111111 2
#140
b11111 .
b11111 G
b1111111111111 L
b1000000000000 K
b1000000000000 5
b1000000000000 <
b1111111111111 2
#150
b111111 .
b111111 G
b11111111111111 L
b10000000000000 K
b10000000000000 5
b10000000000000 <
b11111111111111 2
#160
b1111111 .
b1111111 G
b111111111111111 L
b100000000000000 K
b100000000000000 5
b100000000000000 <
b111111111111111 2
#170
b11111111 .
b11111111 G
b1111111111111111 L
b1000000000000000 K
b1000000000000000 5
b1000000000000000 <
b1111111111111111 2
#180
b0 .
b0 G
b0 ,
b0 F
b0 L
b0 K
b1 2
b1000100011001010110001101101111011001000110010101110010001000000101010001100101011100110111010001110011 9
b0 5
b0 <
#190
b1 ,
b1 F
b0zzzzzzz *
b0zzzzzzz E
b1zzzzzzz )
b1zzzzzzz D
b1 L
b1 K
b10 J
b1 I
b1 5
b1 <
b10 2
b1 1
#200
b11 ,
b11 F
b11 L
b0zzzzzzz )
b0zzzzzzz D
b1zzzzzzz (
b1zzzzzzz C
b10 K
b100 J
b10 I
b10 5
b10 <
b100 2
b10 1
#210
b0zzzzzzz (
b0zzzzzzz C
b1zzzzzzz '
b1zzzzzzz B
b11 K
b1000 J
b11 I
b11 5
b11 <
b1000 2
b100 1
#220
b111 ,
b111 F
b111 L
b0zzzzzzz '
b0zzzzzzz B
b1zzzzzzz &
b1zzzzzzz A
b100 K
b10000 J
b100 I
b100 5
b100 <
b10000 2
b1000 1
#230
b0zzzzzzz &
b0zzzzzzz A
b1zzzzzzz %
b1zzzzzzz @
b101 K
b100000 J
b101 I
b101 5
b101 <
b100000 2
b10000 1
#240
b0zzzzzzz %
b0zzzzzzz @
b1zzzzzzz $
b1zzzzzzz ?
b110 K
b1000000 J
b110 I
b110 5
b110 <
b1000000 2
b100000 1
#250
b0zzzzzzz $
b0zzzzzzz ?
b1zzzzzzz #
b1zzzzzzz >
b111 K
b10000000 J
b111 I
b111 5
b111 <
b10000000 2
b1000000 1
#260
b1111 ,
b1111 F
b1111 L
b1zzzzzzz *
b1zzzzzzz E
b0zzzzzzz #
b0zzzzzzz >
b1000 K
b1 J
b0 I
b1000 5
b1000 <
b100000000 2
b10000000 1
